protonne/__init__.py
protonne/proton.py
protonne/py.typed
protonne-1.0.0.dist-info/METADATA
protonne-1.0.0.dist-info/WHEEL
protonne-1.0.0.dist-info/licenses/LICENSE.txt
protonne-1.0.0.dist-info/RECORD
