Metadata-Version: 2.1
Name: protonne
Version: 1.0.0
Summary: Python bindings for proton vpn's cli.
Project-URL: Homepage, https://github.com/matt-manes/protonne
Project-URL: Documentation, https://github.com/matt-manes/protonne/tree/main/docs
Project-URL: Source code, https://github.com/matt-manes/protonne/tree/main/src/protonne
Author-email: Matt Manes <mattmanes@pm.me>
License-File: LICENSE.txt
Keywords: autorotate,proton,protonvpn,rotate,vpn
Classifier: License :: OSI Approved :: MIT License
Classifier: Operating System :: POSIX :: Linux
Classifier: Programming Language :: Python :: 3
Requires-Python: >=3.10
Requires-Dist: morbin
